pygame_utility/__init__.py
pygame_utility/image_util.py
pygame_utility/maploader.py
pygame_utility/sortkeys.py
pygame_utility-3.0.1.dist-info/LICENSE
pygame_utility-3.0.1.dist-info/METADATA
pygame_utility-3.0.1.dist-info/WHEEL
pygame_utility-3.0.1.dist-info/top_level.txt
pygame_utility-3.0.1.dist-info/RECORD
