Metadata-Version: 2.1
Name: pygame_utility
Version: 3.0.1
Summary: "Package containing simple utility functions for pygame"
Home-page: https://github.com/FluffyRudy/pygame_util
Author: FluffyRudy
Project-URL: Bug Tracker, https://github.com/FluffyRudy/pygame_util/issues
Classifier: Programming Language :: Python :: 3
Classifier: License :: OSI Approved :: MIT License
Classifier: Operating System :: OS Independent
Requires-Python: >=3.6
License-File: LICENSE
Requires-Dist: pygame-ce >=2.0.0
Requires-Dist: pytmx >=3.0.0
